django_db_pooling/__init__.py
django_db_pooling/pooling.py
django_db_pooling-0.0.4.dist-info/METADATA
django_db_pooling-0.0.4.dist-info/RECORD
django_db_pooling-0.0.4.dist-info/WHEEL
django_db_pooling-0.0.4.dist-info/top_level.txt
